README.rst
crowd.py
setup.py
CrowdTimeout.egg-info/PKG-INFO
CrowdTimeout.egg-info/SOURCES.txt
CrowdTimeout.egg-info/dependency_links.txt
CrowdTimeout.egg-info/requires.txt
CrowdTimeout.egg-info/top_level.txt