Metadata-Version: 1.1
Name: CrowdTimeout
Version: 0.9.0
Summary: A python client to the Atlassian Crowd REST API that allows timeouts on the HTTP requests
Home-page: https://github.com/akarnani/python-crowd
Author: Alexander Else
Author-email: aelse@else.id.au
License: BSD
Platform: UNKNOWN
Classifier: Development Status :: 4 - Beta
Classifier: Intended Audience :: Developers
Classifier: License :: OSI Approved :: BSD License
Classifier: Programming Language :: Python
Classifier: Programming Language :: Python :: 2.7
Classifier: Programming Language :: Python :: 3.3
Classifier: Topic :: Software Development :: Libraries :: Python Modules
Classifier: Topic :: System :: Systems Administration :: Authentication/Directory
